pyratlib/__init__.py
pyratlib/processing.py
pyratlib-0.7.6.dist-info/LICENSE
pyratlib-0.7.6.dist-info/METADATA
pyratlib-0.7.6.dist-info/WHEEL
pyratlib-0.7.6.dist-info/top_level.txt
pyratlib-0.7.6.dist-info/RECORD
