Metadata-Version: 2.1
Name: pyratlib
Version: 0.7.6
Summary: PyRat is a user friendly library in python to analyze data from the DeepLabCut. Developed to help researchers unfamiliar with programming can perform animal behavior analysis more simpler.
Home-page: https://github.com/pyratlib/pyrat
License: MIT
Download-URL: https://github.com/pyratlib/pyrat
Keywords: Data analysis,Animal Behavior,Electrophysiology,Tracking,DeepLabCut
Platform: UNKNOWN
Classifier: Development Status :: 4 - Beta
Classifier: Intended Audience :: Developers
Classifier: Topic :: Software Development :: Build Tools
Classifier: License :: OSI Approved :: MIT License
Classifier: Programming Language :: Python :: 3
Classifier: Programming Language :: Python :: 3.4
Classifier: Programming Language :: Python :: 3.5
Classifier: Programming Language :: Python :: 3.6
License-File: LICENSE
Requires-Dist: numpy
Requires-Dist: pandas
Requires-Dist: neo
Requires-Dist: scikit-learn
Requires-Dist: wheel
